secho/__init__.py
secho/color.py
secho/color.pyi
secho-0.2.1.dist-info/LICENSE
secho-0.2.1.dist-info/METADATA
secho-0.2.1.dist-info/WHEEL
secho-0.2.1.dist-info/top_level.txt
secho-0.2.1.dist-info/RECORD
