Metadata-Version: 2.1
Name: secho
Version: 0.2.1
Summary: Bindings for click style echo
Author-email: José Antonio Puértolas Montañés <63794670+j5pu@users.noreply.github.com>
License: MIT
Project-URL: Homepage, https://github.com/mnopi/secho
Requires-Python: >=3.11
License-File: LICENSE
Requires-Dist: typer[all] <1,>=0.9
Provides-Extra: dev
Requires-Dist: pproj[all] ; extra == 'dev'
